README.md
setup.py
BossLike/BossLike.py
BossLike/__init__.py
BossLike.egg-info/PKG-INFO
BossLike.egg-info/SOURCES.txt
BossLike.egg-info/dependency_links.txt
BossLike.egg-info/requires.txt
BossLike.egg-info/top_level.txt