Metadata-Version: 2.1
Name: BossLike
Version: 0.0.6
Summary: BossLike is a ready-made module for working with the api bosslike.ru (for the performer)
Home-page: UNKNOWN
Author: Murat Mazitov
Author-email: j.murat2020@yandex.ru
License: UNKNOWN
Platform: UNKNOWN
Requires-Python: >=3.7
